pymoodef/__init__.py
pymoodef/__main__.py
pymoodef/common.py
pymoodef/data/__init__.py
pymoodef/data/divide.png
pymoodef/data/ops.png
pymoodef/data/questions.csv
pymoodef/data/questions.ini
pymoodef/data/questions.xlsx
pymoodef/data/questions1.csv
pymoodef/data/questions1.ini
pymoodef/datasets.py
pymoodef/ddwtos.py
pymoodef/essay.py
pymoodef/gapselect.py
pymoodef/matching.py
pymoodef/multichoice.py
pymoodef/numerical.py
pymoodef/ordering.py
pymoodef/pymoodef.py
pymoodef/questions.py
pymoodef/shortanswer.py
pymoodef/truefalse.py
pymoodef-0.1.0.dist-info/LICENSE
pymoodef-0.1.0.dist-info/METADATA
pymoodef-0.1.0.dist-info/WHEEL
pymoodef-0.1.0.dist-info/RECORD
