Metadata-Version: 2.1
Name: pymoodef
Version: 0.1.0
Summary: Quiz generation for Moodle in XML.
License: MIT
Author: Jose Samos
Requires-Python: >=3.9
Classifier: License :: OSI Approved :: MIT License
Classifier: Programming Language :: Python :: 3
Classifier: Programming Language :: Python :: 3.9
Classifier: Programming Language :: Python :: 3.10
Classifier: Programming Language :: Python :: 3.11
Classifier: Programming Language :: Python :: 3.12
Requires-Dist: openpyxl (>=3.1.2)
Requires-Dist: pandas (>=2.2.2)
Requires-Dist: pillow (>=10.3.0)
